daqp.cpython-37m-aarch64-linux-gnu.so
daqp-0.7.2.dist-info/LICENSE
daqp-0.7.2.dist-info/METADATA
daqp-0.7.2.dist-info/WHEEL
daqp-0.7.2.dist-info/top_level.txt
daqp-0.7.2.dist-info/RECORD
