Metadata-Version: 2.4
Name: daqp
Version: 0.7.2
Summary: DAQP: A dual active-set QP solver
Home-page: http://github.com/darnstrom/daqp
Author: Daniel Arnström
Author-email: daniel.arnstrom@liu.se
License: MIT
License-File: LICENSE
Dynamic: author
Dynamic: author-email
Dynamic: description
Dynamic: description-content-type
Dynamic: home-page
Dynamic: license
Dynamic: license-file
Dynamic: summary
